pymelcloud/__init__.py
pymelcloud/ata_device.py
pymelcloud/atw_device.py
pymelcloud/client.py
pymelcloud/const.py
pymelcloud/device.py
pymelcloud/erv_device.py
pymelcloud-2.11.0.dist-info/LICENSE
pymelcloud-2.11.0.dist-info/METADATA
pymelcloud-2.11.0.dist-info/WHEEL
pymelcloud-2.11.0.dist-info/top_level.txt
pymelcloud-2.11.0.dist-info/RECORD
