Metadata-Version: 2.1
Name: pymelcloud
Version: 2.11.0
Summary: Python MELCloud interface
Home-page: https://github.com/vilppuvuorinen/pymelcloud
Author: Vilppu Vuorinen
Author-email: vilppu.jotain@gmail.com
License: MIT
Keywords: homeautomation,melcloud
Platform: UNKNOWN
Classifier: Programming Language :: Python :: 3
Classifier: License :: OSI Approved :: MIT License
Classifier: Operating System :: OS Independent
Classifier: Topic :: Software Development :: Libraries :: Application Frameworks
Classifier: Topic :: Home Automation
Requires-Python: >3.5
License-File: LICENSE
Requires-Dist: aiohttp
